fuzzyydictyy/README.MD
fuzzyydictyy/__init__.py
fuzzyydictyy/requirements.txt
fuzzyydictyy/thirdparty.json
fuzzyydictyy-0.12.dist-info/LICENSE.rst
fuzzyydictyy-0.12.dist-info/METADATA
fuzzyydictyy-0.12.dist-info/WHEEL
fuzzyydictyy-0.12.dist-info/top_level.txt
fuzzyydictyy-0.12.dist-info/RECORD
