Metadata-Version: 2.1
Name: fuzzyydictyy
Version: 0.12
Summary: Dict with fuzzy key matching 
Home-page: https://github.com/hansalemaos/fuzzyydictyy
Author: Johannes Fischer
Author-email: aulasparticularesdealemaosp@gmail.com
License: MIT
Keywords: fuzzy,dict
Classifier: Development Status :: 4 - Beta
Classifier: Programming Language :: Python :: 3 :: Only
Classifier: Programming Language :: Python :: 3.10
Classifier: Topic :: Software Development :: Libraries :: Python Modules
Classifier: Topic :: Utilities
License-File: LICENSE.rst
Requires-Dist: rapidfuzz
